bleak/__init__.py
bleak/assigned_numbers.py
bleak/backends/__init__.py
bleak/backends/_manufacturers.py
bleak/backends/bluezdbus/__init__.py
bleak/backends/bluezdbus/advertisement_monitor.py
bleak/backends/bluezdbus/characteristic.py
bleak/backends/bluezdbus/client.py
bleak/backends/bluezdbus/defs.py
bleak/backends/bluezdbus/descriptor.py
bleak/backends/bluezdbus/manager.py
bleak/backends/bluezdbus/scanner.py
bleak/backends/bluezdbus/service.py
bleak/backends/bluezdbus/signals.py
bleak/backends/bluezdbus/utils.py
bleak/backends/bluezdbus/version.py
bleak/backends/characteristic.py
bleak/backends/client.py
bleak/backends/corebluetooth/CentralManagerDelegate.py
bleak/backends/corebluetooth/PeripheralDelegate.py
bleak/backends/corebluetooth/__init__.py
bleak/backends/corebluetooth/characteristic.py
bleak/backends/corebluetooth/client.py
bleak/backends/corebluetooth/descriptor.py
bleak/backends/corebluetooth/scanner.py
bleak/backends/corebluetooth/service.py
bleak/backends/corebluetooth/utils.py
bleak/backends/descriptor.py
bleak/backends/device.py
bleak/backends/p4android/__init__.py
bleak/backends/p4android/characteristic.py
bleak/backends/p4android/client.py
bleak/backends/p4android/defs.py
bleak/backends/p4android/descriptor.py
bleak/backends/p4android/java/com/github/hbldh/bleak/PythonBluetoothGattCallback.java
bleak/backends/p4android/java/com/github/hbldh/bleak/PythonScanCallback.java
bleak/backends/p4android/recipes/bleak/__init__.py
bleak/backends/p4android/recipes/bleak/fix_setup.py
bleak/backends/p4android/scanner.py
bleak/backends/p4android/service.py
bleak/backends/p4android/utils.py
bleak/backends/scanner.py
bleak/backends/service.py
bleak/backends/winrt/__init__.py
bleak/backends/winrt/characteristic.py
bleak/backends/winrt/client.py
bleak/backends/winrt/descriptor.py
bleak/backends/winrt/scanner.py
bleak/backends/winrt/service.py
bleak/exc.py
bleak/py.typed
bleak/uuids.py
bleak-0.21.0.dist-info/LICENSE
bleak-0.21.0.dist-info/METADATA
bleak-0.21.0.dist-info/WHEEL
bleak-0.21.0.dist-info/RECORD
