Metadata-Version: 2.1
Name: bleak
Version: 0.21.0
Summary: Bluetooth Low Energy platform Agnostic Klient
Home-page: https://github.com/hbldh/bleak
License: MIT
Author: Henrik Blidh
Author-email: henrik.blidh@nedomkull.com
Requires-Python: >=3.8,<3.13
Classifier: Development Status :: 4 - Beta
Classifier: Framework :: AsyncIO
Classifier: License :: OSI Approved :: MIT License
Classifier: Operating System :: Android
Classifier: Operating System :: MacOS :: MacOS X
Classifier: Operating System :: Microsoft :: Windows :: Windows 10
Classifier: Operating System :: POSIX :: Linux
Classifier: Programming Language :: Python :: 3
Classifier: Programming Language :: Python :: 3.8
Classifier: Programming Language :: Python :: 3.9
Classifier: Programming Language :: Python :: 3.10
Classifier: Programming Language :: Python :: 3.11
Requires-Dist: async-timeout (>=3.0.0,<5) ; python_version < "3.11"
Requires-Dist: bleak-winrt (>=1.2.0,<2.0.0) ; platform_system == "Windows" and python_version < "3.12"
Requires-Dist: dbus-fast (>=1.83.0,<2.0.0) ; platform_system == "Linux"
Requires-Dist: pyobjc-core (>=9.2,<10.0) ; platform_system == "Darwin"
Requires-Dist: pyobjc-framework-CoreBluetooth (>=9.2,<10.0) ; platform_system == "Darwin"
Requires-Dist: pyobjc-framework-libdispatch (>=9.2,<10.0) ; platform_system == "Darwin"
Requires-Dist: typing-extensions (>=4.7.0) ; python_version < "3.12"
Requires-Dist: winrt-Windows.Devices.Bluetooth (==2.0.0b1) ; platform_system == "Windows" and python_version >= "3.12"
Requires-Dist: winrt-Windows.Devices.Bluetooth.Advertisement (==2.0.0b1) ; platform_system == "Windows" and python_version >= "3.12"
Requires-Dist: winrt-Windows.Devices.Bluetooth.GenericAttributeProfile (==2.0.0b1) ; platform_system == "Windows" and python_version >= "3.12"
Requires-Dist: winrt-Windows.Devices.Enumeration (==2.0.0b1) ; platform_system == "Windows" and python_version >= "3.12"
Requires-Dist: winrt-Windows.Foundation (==2.0.0b1) ; platform_system == "Windows" and python_version >= "3.12"
Requires-Dist: winrt-Windows.Foundation.Collections (==2.0.0b1) ; platform_system == "Windows" and python_version >= "3.12"
Requires-Dist: winrt-Windows.Storage.Streams (==2.0.0b1) ; platform_system == "Windows" and python_version >= "3.12"
Project-URL: Changelog, https://github.com/hbldh/bleak/blob/develop/CHANGELOG.rst
Project-URL: Documentation, https://bleak.readthedocs.io
Project-URL: Issues, https://github.com/hbldh/bleak/issues
Project-URL: Support, https://github.com/hbldh/bleak/discussions
